wrapper_bar/Exceptions.py
wrapper_bar/__init__.py
wrapper_bar/wrapper.py
wrapper_bar-0.1.7.dist-info/LICENSE
wrapper_bar-0.1.7.dist-info/METADATA
wrapper_bar-0.1.7.dist-info/WHEEL
wrapper_bar-0.1.7.dist-info/top_level.txt
wrapper_bar-0.1.7.dist-info/RECORD
