Metadata-Version: 2.1
Name: wrapper-bar
Version: 0.1.7
Summary: Progress Bar with command wrapping
Author-email: Soumyo Deep Gupta <deep.main.ac@gmail.com>
Maintainer-email: Soumyo Deep Gupta <deep.main.ac@gmail.com>
License: MIT License
Project-URL: GitHub, https://github.com/d33p0st/wrapper-bar
Project-URL: Issues, https://github.com/d33p0st/wrapper-bar/issues
Project-URL: Documentation, https://d33p0st.in/documentation/libraries/wrapper_bar#libraries
Keywords: d33pster,progress-bar,wrapper-bar,wrap commands
Classifier: Development Status :: 4 - Beta
Classifier: Topic :: Software Development :: Libraries :: Python Modules
Classifier: Programming Language :: Python :: 3.8
Classifier: Programming Language :: Python :: 3.9
Classifier: Programming Language :: Python :: 3.10
Classifier: Programming Language :: Python :: 3.11
Classifier: Programming Language :: Python :: 3.12
Classifier: License :: OSI Approved :: MIT License
Classifier: Operating System :: OS Independent
Classifier: Intended Audience :: End Users/Desktop
Requires-Python: >=3.8
License-File: LICENSE
Requires-Dist: colorama
Requires-Dist: progressbar
Requires-Dist: requests
Requires-Dist: tqdm
